LICENSE
MANIFEST.in
README.rst
setup.py
threefry/__init__.pxd
threefry/__init__.py
threefry/_threefry.c
threefry/threefry.c
threefry/threefry.h
threefry/threefry.pxd
threefry/threefry.pyx
threefry/version.py
threefry.egg-info/PKG-INFO
threefry.egg-info/SOURCES.txt
threefry.egg-info/dependency_links.txt
threefry.egg-info/top_level.txt