Metadata-Version: 1.0
Name: threefry
Version: 0.1.0
Summary: Threefry random number generator
Home-page: https://pypi.python.org/pypi/threefry
Author: Pierre de Buyl
Author-email: pdebuyl@pdebuyl.be
License: BSD
Platform: UNKNOWN
